DSDMpy/DSDMpy.py
DSDMpy/__init__.py
DSDMpy/update.py
DSDMpy-0.0.2.dist-info/LICENSE
DSDMpy-0.0.2.dist-info/METADATA
DSDMpy-0.0.2.dist-info/WHEEL
DSDMpy-0.0.2.dist-info/top_level.txt
DSDMpy-0.0.2.dist-info/RECORD
