Metadata-Version: 2.1
Name: DSDMpy
Version: 0.0.2
Summary: Library to communicate over wifi using Artnet/Artnet-Repl
Home-page: https://github.com/digitalsputnik/DSDM
Author: Kaspar Kallas
Author-email: kaspar@digitalsputnik.com
License: UNKNOWN
Project-URL: Bug Tracker, https://github.com/digitalsputnik/DSDM/issues
Platform: UNKNOWN
Classifier: Programming Language :: Python :: 3
Classifier: License :: OSI Approved :: BSD License
Classifier: Operating System :: OS Independent
Requires-Python: >=3.7
License-File: LICENSE
Requires-Dist: GitPython
